badl/__init__.py
badl/backend/__init__.py
badl/frontend/.gitignore
badl/frontend/.vscode/extensions.json
badl/frontend/index.html
badl/frontend/package-lock.json
badl/frontend/package.json
badl/frontend/src/App.vue
badl/frontend/src/components/AudioCard.vue
badl/frontend/src/components/DownloadButton.vue
badl/frontend/src/components/TotalProgress.vue
badl/frontend/src/main.js
badl/frontend/src/views/AudioDownload.vue
badl/frontend/src/views/InputVideoNumber.vue
badl/frontend/vite.config.js
badl/main.py
badl/manager/__init__.py
badl/video/__init__.py
badl/video/exceptions.py
badl-0.1.1.dist-info/COPYING
badl-0.1.1.dist-info/METADATA
badl-0.1.1.dist-info/WHEEL
badl-0.1.1.dist-info/RECORD
